{
    "id": "test",
  "purpose": "基礎期第一週，建立有氧耐力與跑步經濟性",
  "week_of_plan": 1,
  "days": [
    {
      "day_index": 1,
      "training_type": "easy_run",
      "day_target": "輕鬆完成5公里跑步，建立有氧基礎",
      "reason": "基礎有氧訓練，為後續訓練打下基礎",
      "training_details": {
        "distance_km": 5.0,
        "time_minutes": 33,
        "pace": "6:35",
        "heart_rate_range": {
          "min": 140,
          "max": 160
        },
        "description": "輕鬆跑，注意保持輕鬆的呼吸和步伐"
      }
    },
    {
      "day_index": 2,
      "training_type": "interval",
      "day_target": "提升速度能力和跑步經濟性",
      "reason": "基礎期初期加入少量高強度間歇訓練，刺激速度發展",
      "tips": "注意熱身和收操，避免受傷",
      "training_details": {
        "repeats": 6,
        "work": {
          "distance_km": 0.4,
          "pace": "5:10",
          "description": "400公尺衝刺跑"
        },
        "recovery": {
          "distance_km": 0.2,
          "time_minutes": 1.5,
          "pace": "7:30",
          "description": "200公尺輕鬆跑恢復"
        }
      }
    },
    {
      "day_index": 3,
      "training_type": "easy_run",
      "day_target": "輕鬆完成6公里跑步，鞏固有氧基礎",
      "reason": "持續建立有氧耐力，促進恢復",
      "training_details": {
        "distance_km": 6.0,
        "time_minutes": 40,
        "pace": "6:40",
        "heart_rate_range": {
          "min": 140,
          "max": 160
        },
        "description": "輕鬆跑，保持穩定配速"
      }
    },
    {
      "day_index": 4,
      "training_type": "rest",
      "day_target": "讓身體充分休息和恢復",
      "reason": "避免連續高強度訓練，讓肌肉得到修復",
      "training_details": {
        "description": "充分休息，可進行輕度拉伸或按摩"
      }
    },
    {
      "day_index": 5,
      "training_type": "tempo",
      "day_target": "提高乳酸閾值，增強耐力",
      "reason": "提升中等強度下的持續奔跑能力",
      "training_details": {
        "distance_km": 5.0,
        "time_minutes": 29,
        "pace": "5:45",
        "heart_rate_range": {
          "min": 160,
          "max": 175
        },
        "description": "節奏跑，保持穩定配速"
      }
    },
    {
      "day_index": 6,
      "training_type": "long_run",
      "day_target": "增強有氧耐力，為後續訓練儲備能量",
      "reason": "長距離跑是基礎期重要的訓練內容，有助於提升有氧能力",
      "training_details": {
        "distance_km": 10.0,
        "time_minutes": 70,
        "pace": "7:00",
        "heart_rate_range": {
          "min": 140,
          "max": 160
        },
        "description": "長距離輕鬆跑，注意補水和能量"
      }
    },
    {
      "day_index": 7,
      "training_type": "recovery_run",
      "day_target": "促進身體恢復，減輕肌肉酸痛",
      "reason": "幫助身體從長距離跑中恢復，避免過度疲勞",
      "training_details": {
        "distance_km": 4.0,
        "time_minutes": 30,
        "pace": "7:30",
        "heart_rate_range": {
          "min": 120,
          "max": 140
        },
        "description": "恢復跑，輕鬆慢跑"
      }
    }
  ],
  "total_distance_reason": "基礎期第一週，總跑量設定為35公里，以建立有氧基礎為主",
  "total_distance_km": 35.0,
  "design_reason": [
    "採用金字塔訓練模式，強化有氧基礎",
    "納入少量高強度短間歇訓練，提升速度能力",
    "長距離跑配速設定在輕鬆區間，確保訓練品質並降低受傷風險"
  ],
  "total_weeks": 12,
  "intensity_total_minutes": {
    "low": 210,
    "medium": 0,
    "high": 12
  }
}
